bottomofthesea/__init__.py
bottomofthesea/bottomofthesea.py
bottomofthesea/preprocess.py
bottomofthesea-0.1.3.dist-info/METADATA
bottomofthesea-0.1.3.dist-info/WHEEL
bottomofthesea-0.1.3.dist-info/entry_points.txt
bottomofthesea-0.1.3.dist-info/RECORD
